drf_misc/__init__.py
drf_misc/admin.py
drf_misc/apps.py
drf_misc/settings.py
drf_misc/core/__init__.py
drf_misc/core/api_exceptions.py
drf_misc/core/api_views.py
drf_misc/core/cache.py
drf_misc/core/fields.py
drf_misc/core/filter_backend.py
drf_misc/core/middlewares.py
drf_misc/core/models.py
drf_misc/core/paginations.py
drf_misc/core/parsers.py
drf_misc/core/permissions.py
drf_misc/core/serializers.py
drf_misc/core/services.py
drf_misc/core/throttling.py
drf_misc/utility/__init__.py
drf_misc/utility/decorators.py
drf_misc/utility/epoch_util.py
drf_misc/utility/misc.py
drf_misc/utility/validator.py
drf_misc-0.5.0.dist-info/METADATA
drf_misc-0.5.0.dist-info/WHEEL
drf_misc-0.5.0.dist-info/licenses/LICENSE
drf_misc-0.5.0.dist-info/RECORD
